MANIFEST.in
README.rst
setup.py
cursedmongo/__init__.py
cursedmongo/tests.py
cursedmongo.egg-info/PKG-INFO
cursedmongo.egg-info/SOURCES.txt
cursedmongo.egg-info/dependency_links.txt
cursedmongo.egg-info/entry_points.txt
cursedmongo.egg-info/not-zip-safe
cursedmongo.egg-info/requires.txt
cursedmongo.egg-info/top_level.txt