Metadata-Version: 1.1
Name: cursedmongo
Version: 0.1
Summary: A curses based MongoDB browser
Home-page: http://github.com/gnublade/cursedmongo
Author: Andy Kilner
Author-email: gnublade@gmail.com
License: GPL
Keywords: curses ncurses mongo mongodb browser
Platform: UNKNOWN
Classifier: Development Status :: 2 - Pre-Alpha
Classifier: Environment :: Console :: Curses
Classifier: License :: OSI Approved :: GNU General Public License (GPL)
Classifier: Programming Language :: Python :: 2.7
Classifier: Topic :: Database :: Front-Ends
